ibl_style/__init__.py
ibl_style/style.py
ibl_style/utils.py
ibl_style-0.0.1.dist-info/LICENSE
ibl_style-0.0.1.dist-info/LICENSE.txt
ibl_style-0.0.1.dist-info/METADATA
ibl_style-0.0.1.dist-info/WHEEL
ibl_style-0.0.1.dist-info/top_level.txt
ibl_style-0.0.1.dist-info/RECORD
