Metadata-Version: 2.1
Name: ibl-style
Version: 0.0.1
Summary: IBL figure styling module
Author-email: IBL staff <info@internationalbrainlab.org>
License: MIT License
Project-URL: Homepage, https://github.com/int-brain-lab/ibl-style
Project-URL: Documentation, https://github.com/int-brain-lab/ibl-style/blob/main/README.md
Project-URL: ChangeLog, https://github.com/int-brain-lab/ibl-style/blob/main/CHANGELOG.md
Project-URL: Bug Tracker, https://github.com/int-brain-lab/ibl-style/issues
Classifier: Programming Language :: Python :: 3
Classifier: License :: OSI Approved :: MIT License
Classifier: Operating System :: OS Independent
Requires-Python: >=3.10
License-File: LICENSE
License-File: LICENSE.txt
Requires-Dist: matplotlib
Requires-Dist: seaborn
Requires-Dist: figrid
